{
  "pollId" : "testcollection",
  "owner" : "Owner",
  "topic" : "Cats",
  "pollStartTime" : "2016-03-17T17:01:29.813Z",
  "pollFinishTime" : "2016-03-17T17:01:29.813Z",
  "questions" :
  [
    {
      "question" : "Do you like cats?",
      "answers" :
      [
        {
          "answer" : "Yes",
          "count" : 11,
          "keysVoted" : [ "111", "222", "333", "444", "555", "666", "777", "888", "999", "101010", "111111" ]
        },
        {
          "answer" : "No",
          "count" : 0,
          "keysVoted" : [ ]
        }
      ]
    }
  ]
}